vmanage_agent/__init__.py
vmanage_agent/cli_keys.py
vmanage_agent/key_manager.py
vmanage_agent/logger.py
vmanage_agent/main.py
vmanage_agent/minion.py
vmanage_agent/utils.py
vmanage_agent-0.2.1.dist-info/METADATA
vmanage_agent-0.2.1.dist-info/WHEEL
vmanage_agent-0.2.1.dist-info/entry_points.txt
vmanage_agent-0.2.1.dist-info/RECORD
