Metadata-Version: 2.4
Name: vmanage-agent
Version: 0.2.1
Summary: Pip module for node to join salt-master
Author-email: Phan Dang <phan.dang@usdatanetworks.com>
Requires-Python: <3.12,>=3.10
Requires-Dist: cryptography<42.0.0,>=41.0.7
Requires-Dist: loguru<0.8.0,>=0.7.2
Requires-Dist: pyjwt<3.0.0,>=2.4.0
Requires-Dist: requests<3.0.0,>=2.27.1
Requires-Dist: tenacity<9.0.0,>=8.3.0
Requires-Dist: toml<0.11.0,>=0.10.2
Requires-Dist: tox<5.0.0,>=4.14.1
Provides-Extra: dev
Requires-Dist: black>=22.8.0; extra == 'dev'
Requires-Dist: flake8<6.0.0,>=5.0.4; extra == 'dev'
Requires-Dist: isort<6.0.0,>=5.13.2; extra == 'dev'
Requires-Dist: pre-commit<3.0.0,>=2.20.0; extra == 'dev'
Requires-Dist: pytest<7.0.0,>=6.2.5; extra == 'dev'
Requires-Dist: scriv[toml]<0.18.0,>=0.17.0; extra == 'dev'
